dalpha/__init__.py
dalpha/agent.py
dalpha/backend_cli.py
dalpha/cobra_cls.py
dalpha/context.py
dalpha/data_update_cls.py
dalpha/data_update_consumer.py
dalpha/dto.py
dalpha/exception.py
dalpha/inference_cls.py
dalpha/kafka_cli.py
dalpha/logging/__init__.py
dalpha/logging/events.py
dalpha/logging/log_formatter.py
dalpha/logging/utils.py
dalpha/message_consumer.py
dalpha/openai_cls.py
dalpha/redis_cli.py
dalpha/redis_cls.py
dalpha/request.py
dalpha/s3.py
dalpha/signal_handler.py
dalpha/update_agent.py
dalpha-0.5.11.dist-info/METADATA
dalpha-0.5.11.dist-info/WHEEL
dalpha-0.5.11.dist-info/RECORD
