Metadata-Version: 2.1
Name: dalpha
Version: 0.5.11
Summary: 
Author: devops
Author-email: devops@dalpha.so
Requires-Python: >=3.8,<4.0
Classifier: Programming Language :: Python :: 3
Classifier: Programming Language :: Python :: 3.8
Classifier: Programming Language :: Python :: 3.9
Classifier: Programming Language :: Python :: 3.10
Classifier: Programming Language :: Python :: 3.11
Classifier: Programming Language :: Python :: 3.12
Requires-Dist: boto3 (>=1.26.137,<2.0.0)
Requires-Dist: build (>=0.10.0,<0.11.0)
Requires-Dist: kafka-python (>=2.0.2,<3.0.0)
Requires-Dist: pydantic (>=2.7.1,<3.0.0)
Requires-Dist: python-json-logger (>=2.0.7,<3.0.0)
Requires-Dist: requests (>=2.30.0,<3.0.0)
Requires-Dist: sentry-sdk (>=1.30.0,<2.0.0)
